shipit/Dockerfile
shipit/__init__.py
shipit/app.py
shipit/cli.py
shipit/commands.py
shipit/shipit.yml
shipit/utils.py
shipit/config/uwsgi-app.ini
shipit_ml-0.6.0.dist-info/AUTHORS.md
shipit_ml-0.6.0.dist-info/LICENSE
shipit_ml-0.6.0.dist-info/METADATA
shipit_ml-0.6.0.dist-info/WHEEL
shipit_ml-0.6.0.dist-info/entry_points.txt
shipit_ml-0.6.0.dist-info/top_level.txt
shipit_ml-0.6.0.dist-info/RECORD
