Metadata-Version: 2.1
Name: shipit-ml
Version: 0.6.0
Summary: Package machine learning models for the web
Home-page: http://github.com/qCaudron/shipit/
Author: Quentin Caudron
Author-email: quentincaudron@gmail.com
License: UNKNOWN
Project-URL: Source, http://github.com/qCaudron/shipit/
Keywords: machine learning scikit keras docker
Platform: UNKNOWN
Classifier: Development Status :: 3 - Alpha
Classifier: Intended Audience :: Developers
Classifier: Topic :: Software Development :: Build Tools
Classifier: License :: OSI Approved :: MIT License
Classifier: Programming Language :: Python :: 3
Requires-Python: !=3.0.*, !=3.1.*, !=3.2.*, !=3.3.*, <4
Requires-Dist: docker (>=3)
Requires-Dist: numpy (>=1)
Requires-Dist: awscli
Requires-Dist: pyyaml (<3.15,>=3.13)
Requires-Dist: delegator.py (>=0.1.1)
